api_config.py
malware_sentinel.py
utils.py
malware_sentinel-2.0.6.dist-info/licenses/LICENSE
malware_sentinel-2.0.6.dist-info/METADATA
malware_sentinel-2.0.6.dist-info/WHEEL
malware_sentinel-2.0.6.dist-info/entry_points.txt
malware_sentinel-2.0.6.dist-info/top_level.txt
malware_sentinel-2.0.6.dist-info/RECORD
