Metadata-Version: 2.4
Name: malware-sentinel
Version: 2.0.6
Summary: An advanced Python-based scanner that allows you to check files, hashes, IP addresses, and domains against VirusTotal.
Author: cyb2rS2c
License: MIT
Classifier: Programming Language :: Python :: 3
Classifier: License :: OSI Approved :: MIT License
Classifier: Operating System :: OS Independent
Requires-Python: >=3.8
License-File: LICENSE
Requires-Dist: requests
Requires-Dist: pyfiglet
Requires-Dist: colorama
Requires-Dist: passlib
Dynamic: license-file
